jyk_timer-0.2.0-py3.8-nspkg.pth
jyk/timer/__init__.py
jyk/timer/core.py
jyk_timer-0.2.0.dist-info/LICENSE
jyk_timer-0.2.0.dist-info/METADATA
jyk_timer-0.2.0.dist-info/WHEEL
jyk_timer-0.2.0.dist-info/namespace_packages.txt
jyk_timer-0.2.0.dist-info/top_level.txt
jyk_timer-0.2.0.dist-info/zip-safe
jyk_timer-0.2.0.dist-info/RECORD
