Metadata-Version: 2.1
Name: jyk-timer
Version: 0.2.0
Summary: jyk timer utils
Home-page: https://git.kongkongss.com/jyk/jyk-timer
Author: Yongkang Jiang
Author-email: jyk.kongkong@gmail.com
License: MIT
Platform: UNKNOWN
Classifier: Programming Language :: Python :: 3.7
Classifier: License :: OSI Approved :: MIT License
Classifier: Operating System :: OS Independent
Requires-Python: >=3.7
